musescore/__init__.py
musescore/musescore.py
musescore-0.0.2.dist-info/LICENSE
musescore-0.0.2.dist-info/METADATA
musescore-0.0.2.dist-info/WHEEL
musescore-0.0.2.dist-info/top_level.txt
musescore-0.0.2.dist-info/RECORD
