Metadata-Version: 2.1
Name: musescore
Version: 0.0.2
Summary: A tool for scraping sheet music from musescore.
Home-page: https://github.com/ryanrudes/musescore
Author: Ryan Rudes
Author-email: ryanrudes@gmail.com
Project-URL: Bug Tracker, https://github.com/ryanrudes/musescore/issues
Classifier: Programming Language :: Python :: 3
Classifier: License :: OSI Approved :: MIT License
Classifier: Operating System :: OS Independent
Requires-Python: >=3.6
License-File: LICENSE
